swh/__init__.py
swh/foo/__init__.py
swh/foo/bar.py
swh/foo/py.typed
swh/foo/tests/__init__.py
swh/foo/tests/test_nothing.py
swh.loader.cvs-0.0.0.dist-info/AUTHORS
swh.loader.cvs-0.0.0.dist-info/LICENSE
swh.loader.cvs-0.0.0.dist-info/METADATA
swh.loader.cvs-0.0.0.dist-info/WHEEL
swh.loader.cvs-0.0.0.dist-info/top_level.txt
swh.loader.cvs-0.0.0.dist-info/RECORD
